<?xml version="1.0" ?>
<root>
	<rooms_with_students_count>
		<room name="Room #0" value="9"/>
		<room name="Room #1" value="7"/>
		<room name="Room #10" value="13"/>
		<room name="Room #100" value="9"/>
		<room name="Room #101" value="10"/>
		<room name="Room #102" value="5"/>
		<room name="Room #103" value="12"/>
		<room name="Room #104" value="12"/>
		<room name="Room #105" value="5"/>
		<room name="Room #106" value="9"/>
		<room name="Room #107" value="12"/>
		<room name="Room #108" value="10"/>
		<room name="Room #109" value="7"/>
		<room name="Room #11" value="12"/>
		<room name="Room #110" value="9"/>
		<room name="Room #111" value="10"/>
		<room name="Room #112" value="11"/>
		<room name="Room #113" value="9"/>
		<room name="Room #114" value="11"/>
		<room name="Room #115" value="9"/>
		<room name="Room #116" value="14"/>
		<room name="Room #117" value="12"/>
		<room name="Room #118" value="10"/>
		<room name="Room #119" value="8"/>
		<room name="Room #12" value="16"/>
		<room name="Room #120" value="12"/>
		<room name="Room #121" value="10"/>
		<room name="Room #122" value="10"/>
		<room name="Room #123" value="12"/>
		<room name="Room #124" value="14"/>
		<room name="Room #125" value="8"/>
		<room name="Room #126" value="11"/>
		<room name="Room #127" value="11"/>
		<room name="Room #128" value="13"/>
		<room name="Room #129" value="8"/>
		<room name="Room #13" value="10"/>
		<room name="Room #130" value="10"/>
		<room name="Room #131" value="8"/>
		<room name="Room #132" value="11"/>
		<room name="Room #133" value="16"/>
		<room name="Room #134" value="4"/>
		<room name="Room #135" value="7"/>
		<room name="Room #136" value="16"/>
		<room name="Room #137" value="11"/>
		<room name="Room #138" value="13"/>
		<room name="Room #139" value="14"/>
		<room name="Room #14" value="7"/>
		<room name="Room #140" value="5"/>
		<room name="Room #141" value="5"/>
		<room name="Room #142" value="11"/>
		<room name="Room #143" value="10"/>
		<room name="Room #144" value="11"/>
		<room name="Room #145" value="16"/>
		<room name="Room #146" value="12"/>
		<room name="Room #147" value="8"/>
		<room name="Room #148" value="7"/>
		<room name="Room #149" value="11"/>
		<room name="Room #15" value="9"/>
		<room name="Room #150" value="6"/>
		<room name="Room #151" value="12"/>
		<room name="Room #152" value="6"/>
		<room name="Room #153" value="7"/>
		<room name="Room #154" value="3"/>
		<room name="Room #155" value="18"/>
		<room name="Room #156" value="9"/>
		<room name="Room #157" value="4"/>
		<room name="Room #158" value="7"/>
		<room name="Room #159" value="7"/>
		<room name="Room #16" value="10"/>
		<room name="Room #160" value="10"/>
		<room name="Room #161" value="15"/>
		<room name="Room #162" value="10"/>
		<room name="Room #163" value="8"/>
		<room name="Room #164" value="8"/>
		<room name="Room #165" value="10"/>
		<room name="Room #166" value="9"/>
		<room name="Room #167" value="7"/>
		<room name="Room #168" value="7"/>
		<room name="Room #169" value="14"/>
		<room name="Room #17" value="9"/>
		<room name="Room #170" value="7"/>
		<room name="Room #171" value="6"/>
		<room name="Room #172" value="10"/>
		<room name="Room #173" value="10"/>
		<room name="Room #174" value="11"/>
		<room name="Room #175" value="13"/>
		<room name="Room #176" value="12"/>
		<room name="Room #177" value="6"/>
		<room name="Room #178" value="4"/>
		<room name="Room #179" value="10"/>
		<room name="Room #18" value="10"/>
		<room name="Room #180" value="8"/>
		<room name="Room #181" value="7"/>
		<room name="Room #182" value="6"/>
		<room name="Room #183" value="7"/>
		<room name="Room #184" value="6"/>
		<room name="Room #185" value="8"/>
		<room name="Room #186" value="6"/>
		<room name="Room #187" value="14"/>
		<room name="Room #188" value="12"/>
		<room name="Room #189" value="12"/>
		<room name="Room #19" value="13"/>
		<room name="Room #190" value="9"/>
		<room name="Room #191" value="7"/>
		<room name="Room #192" value="8"/>
		<room name="Room #193" value="11"/>
		<room name="Room #194" value="8"/>
		<room name="Room #195" value="14"/>
		<room name="Room #196" value="13"/>
		<room name="Room #197" value="19"/>
		<room name="Room #198" value="13"/>
		<room name="Room #199" value="12"/>
		<room name="Room #2" value="9"/>
		<room name="Room #20" value="15"/>
		<room name="Room #200" value="15"/>
		<room name="Room #201" value="13"/>
		<room name="Room #202" value="8"/>
		<room name="Room #203" value="9"/>
		<room name="Room #204" value="9"/>
		<room name="Room #205" value="16"/>
		<room name="Room #206" value="6"/>
		<room name="Room #207" value="11"/>
		<room name="Room #208" value="10"/>
		<room name="Room #209" value="16"/>
		<room name="Room #21" value="15"/>
		<room name="Room #210" value="9"/>
		<room name="Room #211" value="9"/>
		<room name="Room #212" value="8"/>
		<room name="Room #213" value="12"/>
		<room name="Room #214" value="14"/>
		<room name="Room #215" value="10"/>
		<room name="Room #216" value="6"/>
		<room name="Room #217" value="14"/>
		<room name="Room #218" value="8"/>
		<room name="Room #219" value="6"/>
		<room name="Room #22" value="9"/>
		<room name="Room #220" value="10"/>
		<room name="Room #221" value="12"/>
		<room name="Room #222" value="9"/>
		<room name="Room #223" value="6"/>
		<room name="Room #224" value="7"/>
		<room name="Room #225" value="14"/>
		<room name="Room #226" value="8"/>
		<room name="Room #227" value="11"/>
		<room name="Room #228" value="9"/>
		<room name="Room #229" value="7"/>
		<room name="Room #23" value="16"/>
		<room name="Room #230" value="10"/>
		<room name="Room #231" value="11"/>
		<room name="Room #232" value="8"/>
		<room name="Room #233" value="11"/>
		<room name="Room #234" value="11"/>
		<room name="Room #235" value="11"/>
		<room name="Room #236" value="10"/>
		<room name="Room #237" value="16"/>
		<room name="Room #238" value="12"/>
		<room name="Room #239" value="10"/>
		<room name="Room #24" value="14"/>
		<room name="Room #240" value="12"/>
		<room name="Room #241" value="10"/>
		<room name="Room #242" value="13"/>
		<room name="Room #243" value="9"/>
		<room name="Room #244" value="10"/>
		<room name="Room #245" value="10"/>
		<room name="Room #246" value="5"/>
		<room name="Room #247" value="12"/>
		<room name="Room #248" value="8"/>
		<room name="Room #249" value="12"/>
		<room name="Room #25" value="4"/>
		<room name="Room #250" value="12"/>
		<room name="Room #251" value="8"/>
		<room name="Room #252" value="11"/>
		<room name="Room #253" value="13"/>
		<room name="Room #254" value="8"/>
		<room name="Room #255" value="6"/>
		<room name="Room #256" value="11"/>
		<room name="Room #257" value="8"/>
		<room name="Room #258" value="8"/>
		<room name="Room #259" value="14"/>
		<room name="Room #26" value="7"/>
		<room name="Room #260" value="12"/>
		<room name="Room #261" value="7"/>
		<room name="Room #262" value="8"/>
		<room name="Room #263" value="9"/>
		<room name="Room #264" value="7"/>
		<room name="Room #265" value="14"/>
		<room name="Room #266" value="13"/>
		<room name="Room #267" value="7"/>
		<room name="Room #268" value="15"/>
		<room name="Room #269" value="10"/>
		<room name="Room #27" value="6"/>
		<room name="Room #270" value="10"/>
		<room name="Room #271" value="11"/>
		<room name="Room #272" value="8"/>
		<room name="Room #273" value="9"/>
		<room name="Room #274" value="10"/>
		<room name="Room #275" value="12"/>
		<room name="Room #276" value="10"/>
		<room name="Room #277" value="10"/>
		<room name="Room #278" value="9"/>
		<room name="Room #279" value="10"/>
		<room name="Room #28" value="7"/>
		<room name="Room #280" value="11"/>
		<room name="Room #281" value="8"/>
		<room name="Room #282" value="10"/>
		<room name="Room #283" value="7"/>
		<room name="Room #284" value="11"/>
		<room name="Room #285" value="10"/>
		<room name="Room #286" value="6"/>
		<room name="Room #287" value="12"/>
		<room name="Room #288" value="9"/>
		<room name="Room #289" value="15"/>
		<room name="Room #29" value="12"/>
		<room name="Room #290" value="9"/>
		<room name="Room #291" value="10"/>
		<room name="Room #292" value="10"/>
		<room name="Room #293" value="12"/>
		<room name="Room #294" value="11"/>
		<room name="Room #295" value="8"/>
		<room name="Room #296" value="8"/>
		<room name="Room #297" value="13"/>
		<room name="Room #298" value="9"/>
		<room name="Room #299" value="8"/>
		<room name="Room #3" value="5"/>
		<room name="Room #30" value="9"/>
		<room name="Room #300" value="12"/>
		<room name="Room #301" value="10"/>
		<room name="Room #302" value="8"/>
		<room name="Room #303" value="9"/>
		<room name="Room #304" value="11"/>
		<room name="Room #305" value="14"/>
		<room name="Room #306" value="10"/>
		<room name="Room #307" value="10"/>
		<room name="Room #308" value="10"/>
		<room name="Room #309" value="7"/>
		<room name="Room #31" value="13"/>
		<room name="Room #310" value="10"/>
		<room name="Room #311" value="14"/>
		<room name="Room #312" value="11"/>
		<room name="Room #313" value="8"/>
		<room name="Room #314" value="11"/>
		<room name="Room #315" value="10"/>
		<room name="Room #316" value="11"/>
		<room name="Room #317" value="14"/>
		<room name="Room #318" value="15"/>
		<room name="Room #319" value="11"/>
		<room name="Room #32" value="9"/>
		<room name="Room #320" value="7"/>
		<room name="Room #321" value="13"/>
		<room name="Room #322" value="9"/>
		<room name="Room #323" value="13"/>
		<room name="Room #324" value="6"/>
		<room name="Room #325" value="6"/>
		<room name="Room #326" value="18"/>
		<room name="Room #327" value="8"/>
		<room name="Room #328" value="16"/>
		<room name="Room #329" value="10"/>
		<room name="Room #33" value="9"/>
		<room name="Room #330" value="11"/>
		<room name="Room #331" value="12"/>
		<room name="Room #332" value="11"/>
		<room name="Room #333" value="5"/>
		<room name="Room #334" value="10"/>
		<room name="Room #335" value="8"/>
		<room name="Room #336" value="11"/>
		<room name="Room #337" value="11"/>
		<room name="Room #338" value="11"/>
		<room name="Room #339" value="8"/>
		<room name="Room #34" value="9"/>
		<room name="Room #340" value="7"/>
		<room name="Room #341" value="9"/>
		<room name="Room #342" value="14"/>
		<room name="Room #343" value="14"/>
		<room name="Room #344" value="13"/>
		<room name="Room #345" value="4"/>
		<room name="Room #346" value="10"/>
		<room name="Room #347" value="12"/>
		<room name="Room #348" value="12"/>
		<room name="Room #349" value="8"/>
		<room name="Room #35" value="14"/>
		<room name="Room #350" value="11"/>
		<room name="Room #351" value="6"/>
		<room name="Room #352" value="8"/>
		<room name="Room #353" value="4"/>
		<room name="Room #354" value="6"/>
		<room name="Room #355" value="16"/>
		<room name="Room #356" value="16"/>
		<room name="Room #357" value="16"/>
		<room name="Room #358" value="11"/>
		<room name="Room #359" value="18"/>
		<room name="Room #36" value="10"/>
		<room name="Room #360" value="8"/>
		<room name="Room #361" value="6"/>
		<room name="Room #362" value="10"/>
		<room name="Room #363" value="7"/>
		<room name="Room #364" value="8"/>
		<room name="Room #365" value="14"/>
		<room name="Room #366" value="15"/>
		<room name="Room #367" value="11"/>
		<room name="Room #368" value="13"/>
		<room name="Room #369" value="13"/>
		<room name="Room #37" value="12"/>
		<room name="Room #370" value="10"/>
		<room name="Room #371" value="14"/>
		<room name="Room #372" value="7"/>
		<room name="Room #373" value="16"/>
		<room name="Room #374" value="9"/>
		<room name="Room #375" value="8"/>
		<room name="Room #376" value="11"/>
		<room name="Room #377" value="8"/>
		<room name="Room #378" value="11"/>
		<room name="Room #379" value="12"/>
		<room name="Room #38" value="10"/>
		<room name="Room #380" value="8"/>
		<room name="Room #381" value="11"/>
		<room name="Room #382" value="5"/>
		<room name="Room #383" value="5"/>
		<room name="Room #384" value="7"/>
		<room name="Room #385" value="11"/>
		<room name="Room #386" value="11"/>
		<room name="Room #387" value="10"/>
		<room name="Room #388" value="9"/>
		<room name="Room #389" value="9"/>
		<room name="Room #39" value="12"/>
		<room name="Room #390" value="15"/>
		<room name="Room #391" value="10"/>
		<room name="Room #392" value="18"/>
		<room name="Room #393" value="8"/>
		<room name="Room #394" value="9"/>
		<room name="Room #395" value="13"/>
		<room name="Room #396" value="5"/>
		<room name="Room #397" value="8"/>
		<room name="Room #398" value="13"/>
		<room name="Room #399" value="9"/>
		<room name="Room #4" value="11"/>
		<room name="Room #40" value="11"/>
		<room name="Room #400" value="11"/>
		<room name="Room #401" value="7"/>
		<room name="Room #402" value="10"/>
		<room name="Room #403" value="6"/>
		<room name="Room #404" value="7"/>
		<room name="Room #405" value="7"/>
		<room name="Room #406" value="14"/>
		<room name="Room #407" value="10"/>
		<room name="Room #408" value="9"/>
		<room name="Room #409" value="8"/>
		<room name="Room #41" value="15"/>
		<room name="Room #410" value="6"/>
		<room name="Room #411" value="9"/>
		<room name="Room #412" value="13"/>
		<room name="Room #413" value="9"/>
		<room name="Room #414" value="10"/>
		<room name="Room #415" value="12"/>
		<room name="Room #416" value="8"/>
		<room name="Room #417" value="9"/>
		<room name="Room #418" value="15"/>
		<room name="Room #419" value="3"/>
		<room name="Room #42" value="8"/>
		<room name="Room #420" value="6"/>
		<room name="Room #421" value="9"/>
		<room name="Room #422" value="2"/>
		<room name="Room #423" value="16"/>
		<room name="Room #424" value="8"/>
		<room name="Room #425" value="9"/>
		<room name="Room #426" value="10"/>
		<room name="Room #427" value="8"/>
		<room name="Room #428" value="10"/>
		<room name="Room #429" value="10"/>
		<room name="Room #43" value="9"/>
		<room name="Room #430" value="9"/>
		<room name="Room #431" value="11"/>
		<room name="Room #432" value="15"/>
		<room name="Room #433" value="9"/>
		<room name="Room #434" value="9"/>
		<room name="Room #435" value="11"/>
		<room name="Room #436" value="5"/>
		<room name="Room #437" value="16"/>
		<room name="Room #438" value="11"/>
		<room name="Room #439" value="11"/>
		<room name="Room #44" value="16"/>
		<room name="Room #440" value="6"/>
		<room name="Room #441" value="7"/>
		<room name="Room #442" value="15"/>
		<room name="Room #443" value="4"/>
		<room name="Room #444" value="8"/>
		<room name="Room #445" value="8"/>
		<room name="Room #446" value="11"/>
		<room name="Room #447" value="14"/>
		<room name="Room #448" value="18"/>
		<room name="Room #449" value="8"/>
		<room name="Room #45" value="10"/>
		<room name="Room #450" value="6"/>
		<room name="Room #451" value="15"/>
		<room name="Room #452" value="14"/>
		<room name="Room #453" value="10"/>
		<room name="Room #454" value="9"/>
		<room name="Room #455" value="10"/>
		<room name="Room #456" value="6"/>
		<room name="Room #457" value="13"/>
		<room name="Room #458" value="9"/>
		<room name="Room #459" value="11"/>
		<room name="Room #46" value="12"/>
		<room name="Room #460" value="14"/>
		<room name="Room #461" value="8"/>
		<room name="Room #462" value="8"/>
		<room name="Room #463" value="11"/>
		<room name="Room #464" value="16"/>
		<room name="Room #465" value="11"/>
		<room name="Room #466" value="5"/>
		<room name="Room #467" value="11"/>
		<room name="Room #468" value="11"/>
		<room name="Room #469" value="15"/>
		<room name="Room #47" value="9"/>
		<room name="Room #470" value="8"/>
		<room name="Room #471" value="10"/>
		<room name="Room #472" value="8"/>
		<room name="Room #473" value="14"/>
		<room name="Room #474" value="9"/>
		<room name="Room #475" value="9"/>
		<room name="Room #476" value="9"/>
		<room name="Room #477" value="10"/>
		<room name="Room #478" value="6"/>
		<room name="Room #479" value="6"/>
		<room name="Room #48" value="12"/>
		<room name="Room #480" value="6"/>
		<room name="Room #481" value="9"/>
		<room name="Room #483" value="10"/>
		<room name="Room #484" value="4"/>
		<room name="Room #485" value="7"/>
		<room name="Room #486" value="17"/>
		<room name="Room #487" value="4"/>
		<room name="Room #488" value="15"/>
		<room name="Room #489" value="17"/>
		<room name="Room #49" value="3"/>
		<room name="Room #490" value="11"/>
		<room name="Room #491" value="17"/>
		<room name="Room #492" value="8"/>
		<room name="Room #493" value="7"/>
		<room name="Room #494" value="6"/>
		<room name="Room #495" value="6"/>
		<room name="Room #496" value="12"/>
		<room name="Room #497" value="17"/>
		<room name="Room #498" value="4"/>
		<room name="Room #499" value="8"/>
		<room name="Room #5" value="9"/>
		<room name="Room #50" value="6"/>
		<room name="Room #500" value="10"/>
		<room name="Room #501" value="10"/>
		<room name="Room #502" value="8"/>
		<room name="Room #503" value="10"/>
		<room name="Room #504" value="10"/>
		<room name="Room #505" value="15"/>
		<room name="Room #506" value="18"/>
		<room name="Room #507" value="9"/>
		<room name="Room #508" value="9"/>
		<room name="Room #509" value="12"/>
		<room name="Room #51" value="15"/>
		<room name="Room #510" value="14"/>
		<room name="Room #511" value="10"/>
		<room name="Room #512" value="9"/>
		<room name="Room #513" value="12"/>
		<room name="Room #514" value="15"/>
		<room name="Room #515" value="10"/>
		<room name="Room #516" value="13"/>
		<room name="Room #517" value="9"/>
		<room name="Room #518" value="11"/>
		<room name="Room #519" value="12"/>
		<room name="Room #52" value="15"/>
		<room name="Room #520" value="13"/>
		<room name="Room #521" value="16"/>
		<room name="Room #522" value="5"/>
		<room name="Room #523" value="11"/>
		<room name="Room #524" value="8"/>
		<room name="Room #525" value="14"/>
		<room name="Room #526" value="10"/>
		<room name="Room #527" value="13"/>
		<room name="Room #528" value="11"/>
		<room name="Room #529" value="9"/>
		<room name="Room #53" value="9"/>
		<room name="Room #530" value="14"/>
		<room name="Room #531" value="8"/>
		<room name="Room #532" value="12"/>
		<room name="Room #533" value="10"/>
		<room name="Room #534" value="14"/>
		<room name="Room #535" value="15"/>
		<room name="Room #536" value="10"/>
		<room name="Room #537" value="13"/>
		<room name="Room #538" value="5"/>
		<room name="Room #539" value="8"/>
		<room name="Room #54" value="6"/>
		<room name="Room #540" value="5"/>
		<room name="Room #541" value="15"/>
		<room name="Room #542" value="9"/>
		<room name="Room #543" value="14"/>
		<room name="Room #544" value="13"/>
		<room name="Room #545" value="12"/>
		<room name="Room #546" value="10"/>
		<room name="Room #547" value="13"/>
		<room name="Room #548" value="11"/>
		<room name="Room #549" value="8"/>
		<room name="Room #55" value="9"/>
		<room name="Room #550" value="15"/>
		<room name="Room #551" value="8"/>
		<room name="Room #552" value="11"/>
		<room name="Room #553" value="13"/>
		<room name="Room #554" value="7"/>
		<room name="Room #555" value="8"/>
		<room name="Room #556" value="17"/>
		<room name="Room #557" value="14"/>
		<room name="Room #558" value="7"/>
		<room name="Room #559" value="14"/>
		<room name="Room #56" value="13"/>
		<room name="Room #560" value="10"/>
		<room name="Room #561" value="13"/>
		<room name="Room #562" value="9"/>
		<room name="Room #563" value="16"/>
		<room name="Room #564" value="7"/>
		<room name="Room #565" value="9"/>
		<room name="Room #566" value="9"/>
		<room name="Room #567" value="10"/>
		<room name="Room #568" value="7"/>
		<room name="Room #569" value="6"/>
		<room name="Room #57" value="9"/>
		<room name="Room #570" value="11"/>
		<room name="Room #571" value="5"/>
		<room name="Room #572" value="14"/>
		<room name="Room #573" value="17"/>
		<room name="Room #574" value="10"/>
		<room name="Room #575" value="12"/>
		<room name="Room #576" value="10"/>
		<room name="Room #577" value="8"/>
		<room name="Room #578" value="6"/>
		<room name="Room #579" value="7"/>
		<room name="Room #58" value="12"/>
		<room name="Room #580" value="7"/>
		<room name="Room #581" value="13"/>
		<room name="Room #582" value="13"/>
		<room name="Room #583" value="9"/>
		<room name="Room #584" value="11"/>
		<room name="Room #585" value="7"/>
		<room name="Room #586" value="8"/>
		<room name="Room #587" value="9"/>
		<room name="Room #588" value="12"/>
		<room name="Room #589" value="7"/>
		<room name="Room #59" value="9"/>
		<room name="Room #590" value="12"/>
		<room name="Room #591" value="18"/>
		<room name="Room #592" value="11"/>
		<room name="Room #593" value="8"/>
		<room name="Room #594" value="11"/>
		<room name="Room #595" value="7"/>
		<room name="Room #596" value="9"/>
		<room name="Room #597" value="13"/>
		<room name="Room #598" value="9"/>
		<room name="Room #599" value="16"/>
		<room name="Room #6" value="4"/>
		<room name="Room #60" value="9"/>
		<room name="Room #600" value="7"/>
		<room name="Room #601" value="11"/>
		<room name="Room #602" value="10"/>
		<room name="Room #603" value="13"/>
		<room name="Room #604" value="8"/>
		<room name="Room #605" value="8"/>
		<room name="Room #606" value="10"/>
		<room name="Room #607" value="11"/>
		<room name="Room #608" value="14"/>
		<room name="Room #609" value="10"/>
		<room name="Room #61" value="11"/>
		<room name="Room #610" value="8"/>
		<room name="Room #611" value="4"/>
		<room name="Room #612" value="10"/>
		<room name="Room #613" value="11"/>
		<room name="Room #614" value="6"/>
		<room name="Room #615" value="7"/>
		<room name="Room #616" value="7"/>
		<room name="Room #617" value="10"/>
		<room name="Room #618" value="12"/>
		<room name="Room #619" value="9"/>
		<room name="Room #62" value="14"/>
		<room name="Room #620" value="10"/>
		<room name="Room #621" value="10"/>
		<room name="Room #622" value="13"/>
		<room name="Room #623" value="10"/>
		<room name="Room #624" value="8"/>
		<room name="Room #625" value="10"/>
		<room name="Room #626" value="13"/>
		<room name="Room #627" value="15"/>
		<room name="Room #628" value="5"/>
		<room name="Room #629" value="12"/>
		<room name="Room #63" value="9"/>
		<room name="Room #630" value="10"/>
		<room name="Room #631" value="16"/>
		<room name="Room #632" value="9"/>
		<room name="Room #633" value="7"/>
		<room name="Room #634" value="6"/>
		<room name="Room #635" value="8"/>
		<room name="Room #636" value="5"/>
		<room name="Room #637" value="13"/>
		<room name="Room #638" value="7"/>
		<room name="Room #639" value="8"/>
		<room name="Room #64" value="11"/>
		<room name="Room #640" value="6"/>
		<room name="Room #641" value="8"/>
		<room name="Room #642" value="9"/>
		<room name="Room #643" value="11"/>
		<room name="Room #644" value="8"/>
		<room name="Room #645" value="6"/>
		<room name="Room #646" value="14"/>
		<room name="Room #647" value="9"/>
		<room name="Room #648" value="8"/>
		<room name="Room #649" value="9"/>
		<room name="Room #65" value="16"/>
		<room name="Room #650" value="10"/>
		<room name="Room #651" value="10"/>
		<room name="Room #652" value="7"/>
		<room name="Room #653" value="8"/>
		<room name="Room #654" value="12"/>
		<room name="Room #655" value="9"/>
		<room name="Room #656" value="13"/>
		<room name="Room #657" value="15"/>
		<room name="Room #658" value="10"/>
		<room name="Room #659" value="7"/>
		<room name="Room #66" value="6"/>
		<room name="Room #660" value="13"/>
		<room name="Room #661" value="3"/>
		<room name="Room #662" value="7"/>
		<room name="Room #663" value="6"/>
		<room name="Room #664" value="5"/>
		<room name="Room #665" value="14"/>
		<room name="Room #666" value="8"/>
		<room name="Room #667" value="8"/>
		<room name="Room #668" value="8"/>
		<room name="Room #669" value="7"/>
		<room name="Room #67" value="10"/>
		<room name="Room #670" value="10"/>
		<room name="Room #671" value="9"/>
		<room name="Room #672" value="10"/>
		<room name="Room #673" value="9"/>
		<room name="Room #674" value="9"/>
		<room name="Room #675" value="12"/>
		<room name="Room #676" value="8"/>
		<room name="Room #677" value="3"/>
		<room name="Room #678" value="8"/>
		<room name="Room #679" value="14"/>
		<room name="Room #68" value="12"/>
		<room name="Room #680" value="10"/>
		<room name="Room #681" value="4"/>
		<room name="Room #682" value="11"/>
		<room name="Room #683" value="9"/>
		<room name="Room #684" value="10"/>
		<room name="Room #685" value="12"/>
		<room name="Room #686" value="7"/>
		<room name="Room #687" value="8"/>
		<room name="Room #688" value="10"/>
		<room name="Room #689" value="7"/>
		<room name="Room #69" value="12"/>
		<room name="Room #690" value="9"/>
		<room name="Room #691" value="8"/>
		<room name="Room #692" value="10"/>
		<room name="Room #693" value="10"/>
		<room name="Room #694" value="7"/>
		<room name="Room #695" value="15"/>
		<room name="Room #696" value="9"/>
		<room name="Room #697" value="9"/>
		<room name="Room #698" value="5"/>
		<room name="Room #699" value="15"/>
		<room name="Room #7" value="10"/>
		<room name="Room #70" value="12"/>
		<room name="Room #700" value="7"/>
		<room name="Room #701" value="11"/>
		<room name="Room #702" value="11"/>
		<room name="Room #703" value="12"/>
		<room name="Room #704" value="8"/>
		<room name="Room #705" value="9"/>
		<room name="Room #706" value="9"/>
		<room name="Room #707" value="9"/>
		<room name="Room #708" value="11"/>
		<room name="Room #709" value="14"/>
		<room name="Room #71" value="10"/>
		<room name="Room #710" value="4"/>
		<room name="Room #711" value="12"/>
		<room name="Room #712" value="8"/>
		<room name="Room #713" value="12"/>
		<room name="Room #714" value="16"/>
		<room name="Room #715" value="5"/>
		<room name="Room #716" value="14"/>
		<room name="Room #717" value="11"/>
		<room name="Room #718" value="8"/>
		<room name="Room #719" value="14"/>
		<room name="Room #72" value="8"/>
		<room name="Room #720" value="9"/>
		<room name="Room #721" value="7"/>
		<room name="Room #722" value="9"/>
		<room name="Room #723" value="7"/>
		<room name="Room #724" value="12"/>
		<room name="Room #725" value="14"/>
		<room name="Room #726" value="6"/>
		<room name="Room #727" value="8"/>
		<room name="Room #728" value="11"/>
		<room name="Room #729" value="12"/>
		<room name="Room #73" value="20"/>
		<room name="Room #730" value="14"/>
		<room name="Room #731" value="19"/>
		<room name="Room #732" value="6"/>
		<room name="Room #733" value="14"/>
		<room name="Room #734" value="12"/>
		<room name="Room #735" value="8"/>
		<room name="Room #736" value="9"/>
		<room name="Room #737" value="13"/>
		<room name="Room #738" value="12"/>
		<room name="Room #739" value="9"/>
		<room name="Room #74" value="17"/>
		<room name="Room #740" value="14"/>
		<room name="Room #741" value="13"/>
		<room name="Room #742" value="10"/>
		<room name="Room #743" value="12"/>
		<room name="Room #744" value="6"/>
		<room name="Room #745" value="9"/>
		<room name="Room #746" value="9"/>
		<room name="Room #747" value="13"/>
		<room name="Room #748" value="9"/>
		<room name="Room #749" value="13"/>
		<room name="Room #75" value="7"/>
		<room name="Room #750" value="11"/>
		<room name="Room #751" value="12"/>
		<room name="Room #752" value="12"/>
		<room name="Room #753" value="8"/>
		<room name="Room #754" value="5"/>
		<room name="Room #755" value="12"/>
		<room name="Room #756" value="12"/>
		<room name="Room #757" value="9"/>
		<room name="Room #758" value="13"/>
		<room name="Room #759" value="15"/>
		<room name="Room #76" value="6"/>
		<room name="Room #760" value="8"/>
		<room name="Room #761" value="9"/>
		<room name="Room #762" value="11"/>
		<room name="Room #763" value="7"/>
		<room name="Room #764" value="9"/>
		<room name="Room #765" value="8"/>
		<room name="Room #766" value="15"/>
		<room name="Room #767" value="11"/>
		<room name="Room #768" value="11"/>
		<room name="Room #769" value="10"/>
		<room name="Room #77" value="9"/>
		<room name="Room #770" value="9"/>
		<room name="Room #771" value="14"/>
		<room name="Room #772" value="5"/>
		<room name="Room #773" value="11"/>
		<room name="Room #774" value="8"/>
		<room name="Room #775" value="9"/>
		<room name="Room #776" value="7"/>
		<room name="Room #777" value="5"/>
		<room name="Room #778" value="13"/>
		<room name="Room #779" value="13"/>
		<room name="Room #78" value="8"/>
		<room name="Room #780" value="9"/>
		<room name="Room #781" value="13"/>
		<room name="Room #782" value="8"/>
		<room name="Room #783" value="8"/>
		<room name="Room #784" value="12"/>
		<room name="Room #785" value="10"/>
		<room name="Room #786" value="12"/>
		<room name="Room #787" value="8"/>
		<room name="Room #788" value="5"/>
		<room name="Room #789" value="10"/>
		<room name="Room #79" value="6"/>
		<room name="Room #790" value="8"/>
		<room name="Room #791" value="10"/>
		<room name="Room #792" value="7"/>
		<room name="Room #793" value="15"/>
		<room name="Room #794" value="5"/>
		<room name="Room #795" value="12"/>
		<room name="Room #796" value="8"/>
		<room name="Room #797" value="11"/>
		<room name="Room #798" value="5"/>
		<room name="Room #799" value="13"/>
		<room name="Room #8" value="12"/>
		<room name="Room #80" value="7"/>
		<room name="Room #800" value="5"/>
		<room name="Room #801" value="10"/>
		<room name="Room #802" value="12"/>
		<room name="Room #803" value="11"/>
		<room name="Room #804" value="6"/>
		<room name="Room #805" value="10"/>
		<room name="Room #806" value="12"/>
		<room name="Room #807" value="9"/>
		<room name="Room #808" value="11"/>
		<room name="Room #809" value="13"/>
		<room name="Room #81" value="12"/>
		<room name="Room #810" value="2"/>
		<room name="Room #811" value="5"/>
		<room name="Room #812" value="7"/>
		<room name="Room #813" value="20"/>
		<room name="Room #814" value="10"/>
		<room name="Room #815" value="9"/>
		<room name="Room #816" value="10"/>
		<room name="Room #817" value="12"/>
		<room name="Room #818" value="12"/>
		<room name="Room #819" value="9"/>
		<room name="Room #82" value="15"/>
		<room name="Room #820" value="13"/>
		<room name="Room #821" value="11"/>
		<room name="Room #822" value="10"/>
		<room name="Room #823" value="7"/>
		<room name="Room #824" value="9"/>
		<room name="Room #825" value="11"/>
		<room name="Room #826" value="9"/>
		<room name="Room #827" value="7"/>
		<room name="Room #828" value="10"/>
		<room name="Room #829" value="12"/>
		<room name="Room #83" value="11"/>
		<room name="Room #830" value="8"/>
		<room name="Room #831" value="6"/>
		<room name="Room #832" value="14"/>
		<room name="Room #833" value="9"/>
		<room name="Room #834" value="10"/>
		<room name="Room #835" value="16"/>
		<room name="Room #836" value="14"/>
		<room name="Room #837" value="11"/>
		<room name="Room #838" value="14"/>
		<room name="Room #839" value="9"/>
		<room name="Room #84" value="11"/>
		<room name="Room #840" value="8"/>
		<room name="Room #841" value="6"/>
		<room name="Room #842" value="6"/>
		<room name="Room #843" value="12"/>
		<room name="Room #844" value="11"/>
		<room name="Room #845" value="11"/>
		<room name="Room #846" value="11"/>
		<room name="Room #847" value="16"/>
		<room name="Room #848" value="14"/>
		<room name="Room #849" value="9"/>
		<room name="Room #85" value="6"/>
		<room name="Room #850" value="12"/>
		<room name="Room #851" value="6"/>
		<room name="Room #852" value="10"/>
		<room name="Room #853" value="8"/>
		<room name="Room #854" value="13"/>
		<room name="Room #855" value="12"/>
		<room name="Room #856" value="10"/>
		<room name="Room #857" value="6"/>
		<room name="Room #858" value="9"/>
		<room name="Room #859" value="9"/>
		<room name="Room #86" value="9"/>
		<room name="Room #860" value="19"/>
		<room name="Room #861" value="9"/>
		<room name="Room #862" value="6"/>
		<room name="Room #863" value="15"/>
		<room name="Room #864" value="6"/>
		<room name="Room #865" value="12"/>
		<room name="Room #866" value="12"/>
		<room name="Room #867" value="11"/>
		<room name="Room #868" value="9"/>
		<room name="Room #869" value="9"/>
		<room name="Room #87" value="13"/>
		<room name="Room #870" value="6"/>
		<room name="Room #871" value="10"/>
		<room name="Room #872" value="13"/>
		<room name="Room #873" value="4"/>
		<room name="Room #874" value="6"/>
		<room name="Room #875" value="14"/>
		<room name="Room #876" value="6"/>
		<room name="Room #877" value="11"/>
		<room name="Room #878" value="11"/>
		<room name="Room #879" value="15"/>
		<room name="Room #88" value="9"/>
		<room name="Room #880" value="9"/>
		<room name="Room #881" value="11"/>
		<room name="Room #882" value="7"/>
		<room name="Room #883" value="9"/>
		<room name="Room #884" value="14"/>
		<room name="Room #885" value="7"/>
		<room name="Room #886" value="6"/>
		<room name="Room #887" value="7"/>
		<room name="Room #888" value="11"/>
		<room name="Room #889" value="8"/>
		<room name="Room #89" value="7"/>
		<room name="Room #890" value="8"/>
		<room name="Room #891" value="11"/>
		<room name="Room #892" value="10"/>
		<room name="Room #893" value="13"/>
		<room name="Room #894" value="17"/>
		<room name="Room #895" value="6"/>
		<room name="Room #896" value="8"/>
		<room name="Room #897" value="9"/>
		<room name="Room #898" value="12"/>
		<room name="Room #899" value="10"/>
		<room name="Room #9" value="7"/>
		<room name="Room #90" value="11"/>
		<room name="Room #900" value="11"/>
		<room name="Room #901" value="8"/>
		<room name="Room #902" value="5"/>
		<room name="Room #903" value="11"/>
		<room name="Room #904" value="8"/>
		<room name="Room #905" value="19"/>
		<room name="Room #906" value="10"/>
		<room name="Room #907" value="12"/>
		<room name="Room #908" value="7"/>
		<room name="Room #909" value="12"/>
		<room name="Room #91" value="10"/>
		<room name="Room #910" value="10"/>
		<room name="Room #911" value="10"/>
		<room name="Room #912" value="13"/>
		<room name="Room #913" value="3"/>
		<room name="Room #914" value="13"/>
		<room name="Room #915" value="5"/>
		<room name="Room #916" value="8"/>
		<room name="Room #917" value="9"/>
		<room name="Room #918" value="14"/>
		<room name="Room #919" value="5"/>
		<room name="Room #92" value="5"/>
		<room name="Room #920" value="8"/>
		<room name="Room #921" value="10"/>
		<room name="Room #922" value="10"/>
		<room name="Room #923" value="9"/>
		<room name="Room #924" value="12"/>
		<room name="Room #925" value="8"/>
		<room name="Room #926" value="14"/>
		<room name="Room #927" value="9"/>
		<room name="Room #928" value="8"/>
		<room name="Room #929" value="9"/>
		<room name="Room #93" value="12"/>
		<room name="Room #930" value="15"/>
		<room name="Room #931" value="7"/>
		<room name="Room #932" value="9"/>
		<room name="Room #933" value="10"/>
		<room name="Room #934" value="4"/>
		<room name="Room #935" value="10"/>
		<room name="Room #936" value="13"/>
		<room name="Room #937" value="11"/>
		<room name="Room #938" value="12"/>
		<room name="Room #939" value="9"/>
		<room name="Room #94" value="11"/>
		<room name="Room #940" value="7"/>
		<room name="Room #941" value="11"/>
		<room name="Room #942" value="11"/>
		<room name="Room #943" value="5"/>
		<room name="Room #944" value="8"/>
		<room name="Room #945" value="10"/>
		<room name="Room #946" value="11"/>
		<room name="Room #947" value="8"/>
		<room name="Room #948" value="13"/>
		<room name="Room #949" value="10"/>
		<room name="Room #95" value="8"/>
		<room name="Room #950" value="12"/>
		<room name="Room #951" value="8"/>
		<room name="Room #952" value="13"/>
		<room name="Room #953" value="11"/>
		<room name="Room #954" value="7"/>
		<room name="Room #955" value="13"/>
		<room name="Room #956" value="6"/>
		<room name="Room #957" value="9"/>
		<room name="Room #958" value="14"/>
		<room name="Room #959" value="8"/>
		<room name="Room #96" value="9"/>
		<room name="Room #960" value="8"/>
		<room name="Room #961" value="17"/>
		<room name="Room #962" value="9"/>
		<room name="Room #963" value="6"/>
		<room name="Room #964" value="5"/>
		<room name="Room #965" value="15"/>
		<room name="Room #966" value="11"/>
		<room name="Room #967" value="11"/>
		<room name="Room #968" value="17"/>
		<room name="Room #969" value="16"/>
		<room name="Room #97" value="5"/>
		<room name="Room #970" value="6"/>
		<room name="Room #971" value="9"/>
		<room name="Room #972" value="4"/>
		<room name="Room #973" value="9"/>
		<room name="Room #974" value="8"/>
		<room name="Room #975" value="9"/>
		<room name="Room #976" value="7"/>
		<room name="Room #977" value="10"/>
		<room name="Room #978" value="12"/>
		<room name="Room #979" value="10"/>
		<room name="Room #98" value="11"/>
		<room name="Room #980" value="14"/>
		<room name="Room #981" value="12"/>
		<room name="Room #982" value="8"/>
		<room name="Room #983" value="6"/>
		<room name="Room #984" value="13"/>
		<room name="Room #985" value="3"/>
		<room name="Room #986" value="13"/>
		<room name="Room #987" value="7"/>
		<room name="Room #988" value="10"/>
		<room name="Room #989" value="10"/>
		<room name="Room #99" value="8"/>
		<room name="Room #990" value="5"/>
		<room name="Room #991" value="9"/>
		<room name="Room #992" value="13"/>
		<room name="Room #993" value="10"/>
		<room name="Room #994" value="6"/>
		<room name="Room #995" value="13"/>
		<room name="Room #996" value="8"/>
		<room name="Room #997" value="9"/>
		<room name="Room #998" value="14"/>
		<room name="Room #999" value="12"/>
	</rooms_with_students_count>
	<top5_rooms_with_min_average_age>
		<room name="Room #661" value="3000.0"/>
		<room name="Room #913" value="5907.0"/>
		<room name="Room #111" value="10272.6"/>
		<room name="Room #957" value="10786.3"/>
		<room name="Room #773" value="11532.0"/>
	</top5_rooms_with_min_average_age>
	<top5_rooms_with_max_age_diff>
		<room name="Room #712" value="42191.0"/>
		<room name="Room #875" value="42131.0"/>
		<room name="Room #381" value="42066.0"/>
		<room name="Room #213" value="42029.0"/>
		<room name="Room #83" value="42007.0"/>
	</top5_rooms_with_max_age_diff>
	<rooms_with_different_sex_students>
		<room name="Room #0" value="2"/>
		<room name="Room #1" value="2"/>
		<room name="Room #10" value="2"/>
		<room name="Room #100" value="2"/>
		<room name="Room #101" value="2"/>
		<room name="Room #102" value="2"/>
		<room name="Room #103" value="2"/>
		<room name="Room #104" value="2"/>
		<room name="Room #105" value="2"/>
		<room name="Room #106" value="2"/>
		<room name="Room #107" value="2"/>
		<room name="Room #108" value="2"/>
		<room name="Room #109" value="2"/>
		<room name="Room #11" value="2"/>
		<room name="Room #110" value="2"/>
		<room name="Room #111" value="2"/>
		<room name="Room #112" value="2"/>
		<room name="Room #113" value="2"/>
		<room name="Room #114" value="2"/>
		<room name="Room #115" value="2"/>
		<room name="Room #116" value="2"/>
		<room name="Room #117" value="2"/>
		<room name="Room #118" value="2"/>
		<room name="Room #119" value="2"/>
		<room name="Room #12" value="2"/>
		<room name="Room #120" value="2"/>
		<room name="Room #121" value="2"/>
		<room name="Room #122" value="2"/>
		<room name="Room #123" value="2"/>
		<room name="Room #124" value="2"/>
		<room name="Room #125" value="2"/>
		<room name="Room #126" value="2"/>
		<room name="Room #127" value="2"/>
		<room name="Room #128" value="2"/>
		<room name="Room #129" value="2"/>
		<room name="Room #13" value="2"/>
		<room name="Room #130" value="2"/>
		<room name="Room #131" value="2"/>
		<room name="Room #132" value="2"/>
		<room name="Room #133" value="2"/>
		<room name="Room #134" value="2"/>
		<room name="Room #135" value="2"/>
		<room name="Room #136" value="2"/>
		<room name="Room #137" value="2"/>
		<room name="Room #138" value="2"/>
		<room name="Room #139" value="2"/>
		<room name="Room #14" value="2"/>
		<room name="Room #140" value="2"/>
		<room name="Room #141" value="2"/>
		<room name="Room #142" value="2"/>
		<room name="Room #143" value="2"/>
		<room name="Room #144" value="2"/>
		<room name="Room #145" value="2"/>
		<room name="Room #146" value="2"/>
		<room name="Room #147" value="2"/>
		<room name="Room #148" value="2"/>
		<room name="Room #149" value="2"/>
		<room name="Room #15" value="2"/>
		<room name="Room #150" value="2"/>
		<room name="Room #151" value="2"/>
		<room name="Room #152" value="2"/>
		<room name="Room #153" value="2"/>
		<room name="Room #154" value="2"/>
		<room name="Room #155" value="2"/>
		<room name="Room #156" value="2"/>
		<room name="Room #157" value="2"/>
		<room name="Room #158" value="2"/>
		<room name="Room #159" value="2"/>
		<room name="Room #16" value="2"/>
		<room name="Room #160" value="2"/>
		<room name="Room #161" value="2"/>
		<room name="Room #162" value="2"/>
		<room name="Room #163" value="2"/>
		<room name="Room #164" value="2"/>
		<room name="Room #165" value="2"/>
		<room name="Room #166" value="2"/>
		<room name="Room #167" value="2"/>
		<room name="Room #168" value="2"/>
		<room name="Room #169" value="2"/>
		<room name="Room #17" value="2"/>
		<room name="Room #170" value="2"/>
		<room name="Room #171" value="2"/>
		<room name="Room #172" value="2"/>
		<room name="Room #173" value="2"/>
		<room name="Room #174" value="2"/>
		<room name="Room #175" value="2"/>
		<room name="Room #176" value="2"/>
		<room name="Room #177" value="2"/>
		<room name="Room #178" value="2"/>
		<room name="Room #179" value="2"/>
		<room name="Room #18" value="2"/>
		<room name="Room #180" value="2"/>
		<room name="Room #181" value="2"/>
		<room name="Room #182" value="2"/>
		<room name="Room #183" value="2"/>
		<room name="Room #184" value="2"/>
		<room name="Room #185" value="2"/>
		<room name="Room #186" value="2"/>
		<room name="Room #187" value="2"/>
		<room name="Room #188" value="2"/>
		<room name="Room #189" value="2"/>
		<room name="Room #19" value="2"/>
		<room name="Room #190" value="2"/>
		<room name="Room #191" value="2"/>
		<room name="Room #192" value="2"/>
		<room name="Room #193" value="2"/>
		<room name="Room #194" value="2"/>
		<room name="Room #195" value="2"/>
		<room name="Room #196" value="2"/>
		<room name="Room #197" value="2"/>
		<room name="Room #198" value="2"/>
		<room name="Room #199" value="2"/>
		<room name="Room #2" value="2"/>
		<room name="Room #20" value="2"/>
		<room name="Room #200" value="2"/>
		<room name="Room #201" value="2"/>
		<room name="Room #202" value="2"/>
		<room name="Room #203" value="2"/>
		<room name="Room #204" value="2"/>
		<room name="Room #205" value="2"/>
		<room name="Room #206" value="2"/>
		<room name="Room #207" value="2"/>
		<room name="Room #208" value="2"/>
		<room name="Room #209" value="2"/>
		<room name="Room #21" value="2"/>
		<room name="Room #210" value="2"/>
		<room name="Room #211" value="2"/>
		<room name="Room #212" value="2"/>
		<room name="Room #213" value="2"/>
		<room name="Room #214" value="2"/>
		<room name="Room #215" value="2"/>
		<room name="Room #216" value="2"/>
		<room name="Room #217" value="2"/>
		<room name="Room #218" value="2"/>
		<room name="Room #219" value="2"/>
		<room name="Room #22" value="2"/>
		<room name="Room #220" value="2"/>
		<room name="Room #223" value="2"/>
		<room name="Room #224" value="2"/>
		<room name="Room #225" value="2"/>
		<room name="Room #226" value="2"/>
		<room name="Room #227" value="2"/>
		<room name="Room #228" value="2"/>
		<room name="Room #229" value="2"/>
		<room name="Room #23" value="2"/>
		<room name="Room #230" value="2"/>
		<room name="Room #231" value="2"/>
		<room name="Room #232" value="2"/>
		<room name="Room #233" value="2"/>
		<room name="Room #234" value="2"/>
		<room name="Room #235" value="2"/>
		<room name="Room #236" value="2"/>
		<room name="Room #237" value="2"/>
		<room name="Room #238" value="2"/>
		<room name="Room #239" value="2"/>
		<room name="Room #24" value="2"/>
		<room name="Room #240" value="2"/>
		<room name="Room #241" value="2"/>
		<room name="Room #242" value="2"/>
		<room name="Room #243" value="2"/>
		<room name="Room #244" value="2"/>
		<room name="Room #245" value="2"/>
		<room name="Room #246" value="2"/>
		<room name="Room #247" value="2"/>
		<room name="Room #248" value="2"/>
		<room name="Room #249" value="2"/>
		<room name="Room #25" value="2"/>
		<room name="Room #250" value="2"/>
		<room name="Room #251" value="2"/>
		<room name="Room #252" value="2"/>
		<room name="Room #253" value="2"/>
		<room name="Room #254" value="2"/>
		<room name="Room #255" value="2"/>
		<room name="Room #256" value="2"/>
		<room name="Room #257" value="2"/>
		<room name="Room #258" value="2"/>
		<room name="Room #259" value="2"/>
		<room name="Room #26" value="2"/>
		<room name="Room #260" value="2"/>
		<room name="Room #261" value="2"/>
		<room name="Room #262" value="2"/>
		<room name="Room #263" value="2"/>
		<room name="Room #264" value="2"/>
		<room name="Room #265" value="2"/>
		<room name="Room #266" value="2"/>
		<room name="Room #267" value="2"/>
		<room name="Room #268" value="2"/>
		<room name="Room #269" value="2"/>
		<room name="Room #27" value="2"/>
		<room name="Room #270" value="2"/>
		<room name="Room #271" value="2"/>
		<room name="Room #272" value="2"/>
		<room name="Room #273" value="2"/>
		<room name="Room #274" value="2"/>
		<room name="Room #275" value="2"/>
		<room name="Room #276" value="2"/>
		<room name="Room #277" value="2"/>
		<room name="Room #278" value="2"/>
		<room name="Room #279" value="2"/>
		<room name="Room #28" value="2"/>
		<room name="Room #280" value="2"/>
		<room name="Room #281" value="2"/>
		<room name="Room #282" value="2"/>
		<room name="Room #283" value="2"/>
		<room name="Room #284" value="2"/>
		<room name="Room #285" value="2"/>
		<room name="Room #286" value="2"/>
		<room name="Room #287" value="2"/>
		<room name="Room #288" value="2"/>
		<room name="Room #289" value="2"/>
		<room name="Room #29" value="2"/>
		<room name="Room #290" value="2"/>
		<room name="Room #291" value="2"/>
		<room name="Room #292" value="2"/>
		<room name="Room #293" value="2"/>
		<room name="Room #294" value="2"/>
		<room name="Room #295" value="2"/>
		<room name="Room #296" value="2"/>
		<room name="Room #297" value="2"/>
		<room name="Room #298" value="2"/>
		<room name="Room #299" value="2"/>
		<room name="Room #3" value="2"/>
		<room name="Room #30" value="2"/>
		<room name="Room #300" value="2"/>
		<room name="Room #301" value="2"/>
		<room name="Room #302" value="2"/>
		<room name="Room #303" value="2"/>
		<room name="Room #304" value="2"/>
		<room name="Room #305" value="2"/>
		<room name="Room #306" value="2"/>
		<room name="Room #307" value="2"/>
		<room name="Room #308" value="2"/>
		<room name="Room #309" value="2"/>
		<room name="Room #31" value="2"/>
		<room name="Room #310" value="2"/>
		<room name="Room #311" value="2"/>
		<room name="Room #312" value="2"/>
		<room name="Room #313" value="2"/>
		<room name="Room #314" value="2"/>
		<room name="Room #315" value="2"/>
		<room name="Room #316" value="2"/>
		<room name="Room #317" value="2"/>
		<room name="Room #318" value="2"/>
		<room name="Room #319" value="2"/>
		<room name="Room #32" value="2"/>
		<room name="Room #320" value="2"/>
		<room name="Room #321" value="2"/>
		<room name="Room #322" value="2"/>
		<room name="Room #323" value="2"/>
		<room name="Room #324" value="2"/>
		<room name="Room #325" value="2"/>
		<room name="Room #326" value="2"/>
		<room name="Room #327" value="2"/>
		<room name="Room #328" value="2"/>
		<room name="Room #329" value="2"/>
		<room name="Room #33" value="2"/>
		<room name="Room #330" value="2"/>
		<room name="Room #331" value="2"/>
		<room name="Room #332" value="2"/>
		<room name="Room #333" value="2"/>
		<room name="Room #334" value="2"/>
		<room name="Room #335" value="2"/>
		<room name="Room #336" value="2"/>
		<room name="Room #337" value="2"/>
		<room name="Room #338" value="2"/>
		<room name="Room #339" value="2"/>
		<room name="Room #34" value="2"/>
		<room name="Room #340" value="2"/>
		<room name="Room #341" value="2"/>
		<room name="Room #342" value="2"/>
		<room name="Room #343" value="2"/>
		<room name="Room #344" value="2"/>
		<room name="Room #345" value="2"/>
		<room name="Room #346" value="2"/>
		<room name="Room #347" value="2"/>
		<room name="Room #348" value="2"/>
		<room name="Room #349" value="2"/>
		<room name="Room #35" value="2"/>
		<room name="Room #350" value="2"/>
		<room name="Room #351" value="2"/>
		<room name="Room #352" value="2"/>
		<room name="Room #353" value="2"/>
		<room name="Room #354" value="2"/>
		<room name="Room #355" value="2"/>
		<room name="Room #356" value="2"/>
		<room name="Room #357" value="2"/>
		<room name="Room #358" value="2"/>
		<room name="Room #359" value="2"/>
		<room name="Room #36" value="2"/>
		<room name="Room #360" value="2"/>
		<room name="Room #361" value="2"/>
		<room name="Room #362" value="2"/>
		<room name="Room #363" value="2"/>
		<room name="Room #364" value="2"/>
		<room name="Room #365" value="2"/>
		<room name="Room #366" value="2"/>
		<room name="Room #367" value="2"/>
		<room name="Room #368" value="2"/>
		<room name="Room #369" value="2"/>
		<room name="Room #37" value="2"/>
		<room name="Room #370" value="2"/>
		<room name="Room #371" value="2"/>
		<room name="Room #372" value="2"/>
		<room name="Room #373" value="2"/>
		<room name="Room #374" value="2"/>
		<room name="Room #375" value="2"/>
		<room name="Room #376" value="2"/>
		<room name="Room #377" value="2"/>
		<room name="Room #378" value="2"/>
		<room name="Room #379" value="2"/>
		<room name="Room #38" value="2"/>
		<room name="Room #380" value="2"/>
		<room name="Room #381" value="2"/>
		<room name="Room #382" value="2"/>
		<room name="Room #383" value="2"/>
		<room name="Room #384" value="2"/>
		<room name="Room #385" value="2"/>
		<room name="Room #386" value="2"/>
		<room name="Room #387" value="2"/>
		<room name="Room #388" value="2"/>
		<room name="Room #389" value="2"/>
		<room name="Room #39" value="2"/>
		<room name="Room #390" value="2"/>
		<room name="Room #391" value="2"/>
		<room name="Room #392" value="2"/>
		<room name="Room #393" value="2"/>
		<room name="Room #394" value="2"/>
		<room name="Room #395" value="2"/>
		<room name="Room #397" value="2"/>
		<room name="Room #398" value="2"/>
		<room name="Room #399" value="2"/>
		<room name="Room #4" value="2"/>
		<room name="Room #40" value="2"/>
		<room name="Room #400" value="2"/>
		<room name="Room #401" value="2"/>
		<room name="Room #402" value="2"/>
		<room name="Room #403" value="2"/>
		<room name="Room #404" value="2"/>
		<room name="Room #405" value="2"/>
		<room name="Room #406" value="2"/>
		<room name="Room #407" value="2"/>
		<room name="Room #408" value="2"/>
		<room name="Room #409" value="2"/>
		<room name="Room #41" value="2"/>
		<room name="Room #410" value="2"/>
		<room name="Room #411" value="2"/>
		<room name="Room #412" value="2"/>
		<room name="Room #413" value="2"/>
		<room name="Room #414" value="2"/>
		<room name="Room #415" value="2"/>
		<room name="Room #416" value="2"/>
		<room name="Room #417" value="2"/>
		<room name="Room #418" value="2"/>
		<room name="Room #42" value="2"/>
		<room name="Room #420" value="2"/>
		<room name="Room #421" value="2"/>
		<room name="Room #422" value="2"/>
		<room name="Room #423" value="2"/>
		<room name="Room #424" value="2"/>
		<room name="Room #425" value="2"/>
		<room name="Room #426" value="2"/>
		<room name="Room #427" value="2"/>
		<room name="Room #428" value="2"/>
		<room name="Room #429" value="2"/>
		<room name="Room #43" value="2"/>
		<room name="Room #430" value="2"/>
		<room name="Room #431" value="2"/>
		<room name="Room #432" value="2"/>
		<room name="Room #433" value="2"/>
		<room name="Room #434" value="2"/>
		<room name="Room #435" value="2"/>
		<room name="Room #436" value="2"/>
		<room name="Room #437" value="2"/>
		<room name="Room #438" value="2"/>
		<room name="Room #439" value="2"/>
		<room name="Room #44" value="2"/>
		<room name="Room #440" value="2"/>
		<room name="Room #441" value="2"/>
		<room name="Room #442" value="2"/>
		<room name="Room #443" value="2"/>
		<room name="Room #444" value="2"/>
		<room name="Room #445" value="2"/>
		<room name="Room #446" value="2"/>
		<room name="Room #447" value="2"/>
		<room name="Room #448" value="2"/>
		<room name="Room #449" value="2"/>
		<room name="Room #45" value="2"/>
		<room name="Room #450" value="2"/>
		<room name="Room #451" value="2"/>
		<room name="Room #452" value="2"/>
		<room name="Room #453" value="2"/>
		<room name="Room #454" value="2"/>
		<room name="Room #455" value="2"/>
		<room name="Room #456" value="2"/>
		<room name="Room #457" value="2"/>
		<room name="Room #458" value="2"/>
		<room name="Room #459" value="2"/>
		<room name="Room #46" value="2"/>
		<room name="Room #460" value="2"/>
		<room name="Room #461" value="2"/>
		<room name="Room #462" value="2"/>
		<room name="Room #463" value="2"/>
		<room name="Room #464" value="2"/>
		<room name="Room #465" value="2"/>
		<room name="Room #466" value="2"/>
		<room name="Room #467" value="2"/>
		<room name="Room #468" value="2"/>
		<room name="Room #469" value="2"/>
		<room name="Room #47" value="2"/>
		<room name="Room #470" value="2"/>
		<room name="Room #471" value="2"/>
		<room name="Room #472" value="2"/>
		<room name="Room #473" value="2"/>
		<room name="Room #474" value="2"/>
		<room name="Room #475" value="2"/>
		<room name="Room #476" value="2"/>
		<room name="Room #477" value="2"/>
		<room name="Room #478" value="2"/>
		<room name="Room #479" value="2"/>
		<room name="Room #48" value="2"/>
		<room name="Room #480" value="2"/>
		<room name="Room #481" value="2"/>
		<room name="Room #483" value="2"/>
		<room name="Room #485" value="2"/>
		<room name="Room #486" value="2"/>
		<room name="Room #487" value="2"/>
		<room name="Room #488" value="2"/>
		<room name="Room #489" value="2"/>
		<room name="Room #49" value="2"/>
		<room name="Room #490" value="2"/>
		<room name="Room #491" value="2"/>
		<room name="Room #492" value="2"/>
		<room name="Room #493" value="2"/>
		<room name="Room #494" value="2"/>
		<room name="Room #495" value="2"/>
		<room name="Room #496" value="2"/>
		<room name="Room #497" value="2"/>
		<room name="Room #498" value="2"/>
		<room name="Room #499" value="2"/>
		<room name="Room #5" value="2"/>
		<room name="Room #50" value="2"/>
		<room name="Room #500" value="2"/>
		<room name="Room #501" value="2"/>
		<room name="Room #502" value="2"/>
		<room name="Room #503" value="2"/>
		<room name="Room #504" value="2"/>
		<room name="Room #505" value="2"/>
		<room name="Room #506" value="2"/>
		<room name="Room #507" value="2"/>
		<room name="Room #508" value="2"/>
		<room name="Room #509" value="2"/>
		<room name="Room #51" value="2"/>
		<room name="Room #510" value="2"/>
		<room name="Room #511" value="2"/>
		<room name="Room #512" value="2"/>
		<room name="Room #513" value="2"/>
		<room name="Room #514" value="2"/>
		<room name="Room #515" value="2"/>
		<room name="Room #516" value="2"/>
		<room name="Room #517" value="2"/>
		<room name="Room #518" value="2"/>
		<room name="Room #519" value="2"/>
		<room name="Room #52" value="2"/>
		<room name="Room #520" value="2"/>
		<room name="Room #521" value="2"/>
		<room name="Room #522" value="2"/>
		<room name="Room #523" value="2"/>
		<room name="Room #524" value="2"/>
		<room name="Room #525" value="2"/>
		<room name="Room #526" value="2"/>
		<room name="Room #527" value="2"/>
		<room name="Room #528" value="2"/>
		<room name="Room #529" value="2"/>
		<room name="Room #53" value="2"/>
		<room name="Room #530" value="2"/>
		<room name="Room #531" value="2"/>
		<room name="Room #532" value="2"/>
		<room name="Room #533" value="2"/>
		<room name="Room #534" value="2"/>
		<room name="Room #535" value="2"/>
		<room name="Room #536" value="2"/>
		<room name="Room #537" value="2"/>
		<room name="Room #538" value="2"/>
		<room name="Room #539" value="2"/>
		<room name="Room #54" value="2"/>
		<room name="Room #540" value="2"/>
		<room name="Room #541" value="2"/>
		<room name="Room #542" value="2"/>
		<room name="Room #543" value="2"/>
		<room name="Room #544" value="2"/>
		<room name="Room #545" value="2"/>
		<room name="Room #546" value="2"/>
		<room name="Room #547" value="2"/>
		<room name="Room #548" value="2"/>
		<room name="Room #549" value="2"/>
		<room name="Room #55" value="2"/>
		<room name="Room #550" value="2"/>
		<room name="Room #551" value="2"/>
		<room name="Room #552" value="2"/>
		<room name="Room #553" value="2"/>
		<room name="Room #554" value="2"/>
		<room name="Room #555" value="2"/>
		<room name="Room #556" value="2"/>
		<room name="Room #557" value="2"/>
		<room name="Room #558" value="2"/>
		<room name="Room #559" value="2"/>
		<room name="Room #56" value="2"/>
		<room name="Room #560" value="2"/>
		<room name="Room #561" value="2"/>
		<room name="Room #562" value="2"/>
		<room name="Room #563" value="2"/>
		<room name="Room #564" value="2"/>
		<room name="Room #565" value="2"/>
		<room name="Room #566" value="2"/>
		<room name="Room #567" value="2"/>
		<room name="Room #568" value="2"/>
		<room name="Room #569" value="2"/>
		<room name="Room #57" value="2"/>
		<room name="Room #570" value="2"/>
		<room name="Room #571" value="2"/>
		<room name="Room #572" value="2"/>
		<room name="Room #573" value="2"/>
		<room name="Room #574" value="2"/>
		<room name="Room #575" value="2"/>
		<room name="Room #576" value="2"/>
		<room name="Room #577" value="2"/>
		<room name="Room #578" value="2"/>
		<room name="Room #58" value="2"/>
		<room name="Room #580" value="2"/>
		<room name="Room #581" value="2"/>
		<room name="Room #582" value="2"/>
		<room name="Room #583" value="2"/>
		<room name="Room #584" value="2"/>
		<room name="Room #585" value="2"/>
		<room name="Room #586" value="2"/>
		<room name="Room #587" value="2"/>
		<room name="Room #588" value="2"/>
		<room name="Room #589" value="2"/>
		<room name="Room #59" value="2"/>
		<room name="Room #590" value="2"/>
		<room name="Room #591" value="2"/>
		<room name="Room #592" value="2"/>
		<room name="Room #593" value="2"/>
		<room name="Room #594" value="2"/>
		<room name="Room #595" value="2"/>
		<room name="Room #596" value="2"/>
		<room name="Room #597" value="2"/>
		<room name="Room #598" value="2"/>
		<room name="Room #599" value="2"/>
		<room name="Room #60" value="2"/>
		<room name="Room #600" value="2"/>
		<room name="Room #601" value="2"/>
		<room name="Room #602" value="2"/>
		<room name="Room #603" value="2"/>
		<room name="Room #604" value="2"/>
		<room name="Room #605" value="2"/>
		<room name="Room #606" value="2"/>
		<room name="Room #607" value="2"/>
		<room name="Room #608" value="2"/>
		<room name="Room #609" value="2"/>
		<room name="Room #61" value="2"/>
		<room name="Room #610" value="2"/>
		<room name="Room #611" value="2"/>
		<room name="Room #612" value="2"/>
		<room name="Room #613" value="2"/>
		<room name="Room #614" value="2"/>
		<room name="Room #615" value="2"/>
		<room name="Room #616" value="2"/>
		<room name="Room #617" value="2"/>
		<room name="Room #618" value="2"/>
		<room name="Room #619" value="2"/>
		<room name="Room #62" value="2"/>
		<room name="Room #620" value="2"/>
		<room name="Room #621" value="2"/>
		<room name="Room #622" value="2"/>
		<room name="Room #624" value="2"/>
		<room name="Room #625" value="2"/>
		<room name="Room #626" value="2"/>
		<room name="Room #627" value="2"/>
		<room name="Room #628" value="2"/>
		<room name="Room #629" value="2"/>
		<room name="Room #63" value="2"/>
		<room name="Room #630" value="2"/>
		<room name="Room #631" value="2"/>
		<room name="Room #632" value="2"/>
		<room name="Room #633" value="2"/>
		<room name="Room #634" value="2"/>
		<room name="Room #635" value="2"/>
		<room name="Room #636" value="2"/>
		<room name="Room #637" value="2"/>
		<room name="Room #638" value="2"/>
		<room name="Room #639" value="2"/>
		<room name="Room #64" value="2"/>
		<room name="Room #640" value="2"/>
		<room name="Room #641" value="2"/>
		<room name="Room #642" value="2"/>
		<room name="Room #643" value="2"/>
		<room name="Room #644" value="2"/>
		<room name="Room #645" value="2"/>
		<room name="Room #646" value="2"/>
		<room name="Room #647" value="2"/>
		<room name="Room #648" value="2"/>
		<room name="Room #649" value="2"/>
		<room name="Room #65" value="2"/>
		<room name="Room #650" value="2"/>
		<room name="Room #651" value="2"/>
		<room name="Room #652" value="2"/>
		<room name="Room #653" value="2"/>
		<room name="Room #654" value="2"/>
		<room name="Room #655" value="2"/>
		<room name="Room #656" value="2"/>
		<room name="Room #657" value="2"/>
		<room name="Room #658" value="2"/>
		<room name="Room #659" value="2"/>
		<room name="Room #66" value="2"/>
		<room name="Room #660" value="2"/>
		<room name="Room #661" value="2"/>
		<room name="Room #662" value="2"/>
		<room name="Room #663" value="2"/>
		<room name="Room #664" value="2"/>
		<room name="Room #665" value="2"/>
		<room name="Room #666" value="2"/>
		<room name="Room #667" value="2"/>
		<room name="Room #668" value="2"/>
		<room name="Room #669" value="2"/>
		<room name="Room #67" value="2"/>
		<room name="Room #670" value="2"/>
		<room name="Room #671" value="2"/>
		<room name="Room #672" value="2"/>
		<room name="Room #673" value="2"/>
		<room name="Room #674" value="2"/>
		<room name="Room #675" value="2"/>
		<room name="Room #676" value="2"/>
		<room name="Room #677" value="2"/>
		<room name="Room #678" value="2"/>
		<room name="Room #679" value="2"/>
		<room name="Room #68" value="2"/>
		<room name="Room #680" value="2"/>
		<room name="Room #681" value="2"/>
		<room name="Room #682" value="2"/>
		<room name="Room #683" value="2"/>
		<room name="Room #684" value="2"/>
		<room name="Room #685" value="2"/>
		<room name="Room #686" value="2"/>
		<room name="Room #687" value="2"/>
		<room name="Room #688" value="2"/>
		<room name="Room #689" value="2"/>
		<room name="Room #69" value="2"/>
		<room name="Room #690" value="2"/>
		<room name="Room #691" value="2"/>
		<room name="Room #692" value="2"/>
		<room name="Room #693" value="2"/>
		<room name="Room #694" value="2"/>
		<room name="Room #695" value="2"/>
		<room name="Room #696" value="2"/>
		<room name="Room #697" value="2"/>
		<room name="Room #698" value="2"/>
		<room name="Room #699" value="2"/>
		<room name="Room #7" value="2"/>
		<room name="Room #70" value="2"/>
		<room name="Room #700" value="2"/>
		<room name="Room #701" value="2"/>
		<room name="Room #702" value="2"/>
		<room name="Room #703" value="2"/>
		<room name="Room #704" value="2"/>
		<room name="Room #705" value="2"/>
		<room name="Room #706" value="2"/>
		<room name="Room #707" value="2"/>
		<room name="Room #708" value="2"/>
		<room name="Room #709" value="2"/>
		<room name="Room #71" value="2"/>
		<room name="Room #710" value="2"/>
		<room name="Room #711" value="2"/>
		<room name="Room #712" value="2"/>
		<room name="Room #713" value="2"/>
		<room name="Room #714" value="2"/>
		<room name="Room #715" value="2"/>
		<room name="Room #716" value="2"/>
		<room name="Room #717" value="2"/>
		<room name="Room #718" value="2"/>
		<room name="Room #719" value="2"/>
		<room name="Room #72" value="2"/>
		<room name="Room #720" value="2"/>
		<room name="Room #721" value="2"/>
		<room name="Room #722" value="2"/>
		<room name="Room #723" value="2"/>
		<room name="Room #724" value="2"/>
		<room name="Room #725" value="2"/>
		<room name="Room #726" value="2"/>
		<room name="Room #727" value="2"/>
		<room name="Room #728" value="2"/>
		<room name="Room #729" value="2"/>
		<room name="Room #73" value="2"/>
		<room name="Room #730" value="2"/>
		<room name="Room #731" value="2"/>
		<room name="Room #732" value="2"/>
		<room name="Room #733" value="2"/>
		<room name="Room #734" value="2"/>
		<room name="Room #735" value="2"/>
		<room name="Room #737" value="2"/>
		<room name="Room #738" value="2"/>
		<room name="Room #739" value="2"/>
		<room name="Room #74" value="2"/>
		<room name="Room #740" value="2"/>
		<room name="Room #741" value="2"/>
		<room name="Room #742" value="2"/>
		<room name="Room #743" value="2"/>
		<room name="Room #744" value="2"/>
		<room name="Room #745" value="2"/>
		<room name="Room #746" value="2"/>
		<room name="Room #747" value="2"/>
		<room name="Room #748" value="2"/>
		<room name="Room #749" value="2"/>
		<room name="Room #75" value="2"/>
		<room name="Room #750" value="2"/>
		<room name="Room #751" value="2"/>
		<room name="Room #752" value="2"/>
		<room name="Room #753" value="2"/>
		<room name="Room #754" value="2"/>
		<room name="Room #755" value="2"/>
		<room name="Room #756" value="2"/>
		<room name="Room #757" value="2"/>
		<room name="Room #758" value="2"/>
		<room name="Room #759" value="2"/>
		<room name="Room #76" value="2"/>
		<room name="Room #760" value="2"/>
		<room name="Room #761" value="2"/>
		<room name="Room #762" value="2"/>
		<room name="Room #763" value="2"/>
		<room name="Room #764" value="2"/>
		<room name="Room #765" value="2"/>
		<room name="Room #766" value="2"/>
		<room name="Room #767" value="2"/>
		<room name="Room #768" value="2"/>
		<room name="Room #769" value="2"/>
		<room name="Room #77" value="2"/>
		<room name="Room #770" value="2"/>
		<room name="Room #771" value="2"/>
		<room name="Room #772" value="2"/>
		<room name="Room #773" value="2"/>
		<room name="Room #774" value="2"/>
		<room name="Room #775" value="2"/>
		<room name="Room #776" value="2"/>
		<room name="Room #777" value="2"/>
		<room name="Room #778" value="2"/>
		<room name="Room #779" value="2"/>
		<room name="Room #78" value="2"/>
		<room name="Room #780" value="2"/>
		<room name="Room #781" value="2"/>
		<room name="Room #782" value="2"/>
		<room name="Room #783" value="2"/>
		<room name="Room #784" value="2"/>
		<room name="Room #785" value="2"/>
		<room name="Room #786" value="2"/>
		<room name="Room #787" value="2"/>
		<room name="Room #788" value="2"/>
		<room name="Room #789" value="2"/>
		<room name="Room #79" value="2"/>
		<room name="Room #790" value="2"/>
		<room name="Room #791" value="2"/>
		<room name="Room #792" value="2"/>
		<room name="Room #793" value="2"/>
		<room name="Room #794" value="2"/>
		<room name="Room #795" value="2"/>
		<room name="Room #796" value="2"/>
		<room name="Room #797" value="2"/>
		<room name="Room #798" value="2"/>
		<room name="Room #799" value="2"/>
		<room name="Room #8" value="2"/>
		<room name="Room #80" value="2"/>
		<room name="Room #800" value="2"/>
		<room name="Room #801" value="2"/>
		<room name="Room #802" value="2"/>
		<room name="Room #803" value="2"/>
		<room name="Room #804" value="2"/>
		<room name="Room #805" value="2"/>
		<room name="Room #806" value="2"/>
		<room name="Room #807" value="2"/>
		<room name="Room #808" value="2"/>
		<room name="Room #809" value="2"/>
		<room name="Room #81" value="2"/>
		<room name="Room #810" value="2"/>
		<room name="Room #811" value="2"/>
		<room name="Room #812" value="2"/>
		<room name="Room #813" value="2"/>
		<room name="Room #814" value="2"/>
		<room name="Room #815" value="2"/>
		<room name="Room #816" value="2"/>
		<room name="Room #817" value="2"/>
		<room name="Room #818" value="2"/>
		<room name="Room #819" value="2"/>
		<room name="Room #82" value="2"/>
		<room name="Room #820" value="2"/>
		<room name="Room #821" value="2"/>
		<room name="Room #822" value="2"/>
		<room name="Room #823" value="2"/>
		<room name="Room #824" value="2"/>
		<room name="Room #825" value="2"/>
		<room name="Room #826" value="2"/>
		<room name="Room #827" value="2"/>
		<room name="Room #828" value="2"/>
		<room name="Room #829" value="2"/>
		<room name="Room #83" value="2"/>
		<room name="Room #830" value="2"/>
		<room name="Room #831" value="2"/>
		<room name="Room #832" value="2"/>
		<room name="Room #833" value="2"/>
		<room name="Room #834" value="2"/>
		<room name="Room #835" value="2"/>
		<room name="Room #836" value="2"/>
		<room name="Room #837" value="2"/>
		<room name="Room #838" value="2"/>
		<room name="Room #839" value="2"/>
		<room name="Room #84" value="2"/>
		<room name="Room #840" value="2"/>
		<room name="Room #841" value="2"/>
		<room name="Room #842" value="2"/>
		<room name="Room #843" value="2"/>
		<room name="Room #844" value="2"/>
		<room name="Room #845" value="2"/>
		<room name="Room #846" value="2"/>
		<room name="Room #847" value="2"/>
		<room name="Room #848" value="2"/>
		<room name="Room #849" value="2"/>
		<room name="Room #85" value="2"/>
		<room name="Room #850" value="2"/>
		<room name="Room #851" value="2"/>
		<room name="Room #852" value="2"/>
		<room name="Room #853" value="2"/>
		<room name="Room #854" value="2"/>
		<room name="Room #855" value="2"/>
		<room name="Room #856" value="2"/>
		<room name="Room #857" value="2"/>
		<room name="Room #858" value="2"/>
		<room name="Room #859" value="2"/>
		<room name="Room #86" value="2"/>
		<room name="Room #860" value="2"/>
		<room name="Room #861" value="2"/>
		<room name="Room #862" value="2"/>
		<room name="Room #863" value="2"/>
		<room name="Room #864" value="2"/>
		<room name="Room #865" value="2"/>
		<room name="Room #866" value="2"/>
		<room name="Room #867" value="2"/>
		<room name="Room #868" value="2"/>
		<room name="Room #869" value="2"/>
		<room name="Room #87" value="2"/>
		<room name="Room #870" value="2"/>
		<room name="Room #871" value="2"/>
		<room name="Room #872" value="2"/>
		<room name="Room #873" value="2"/>
		<room name="Room #874" value="2"/>
		<room name="Room #875" value="2"/>
		<room name="Room #876" value="2"/>
		<room name="Room #877" value="2"/>
		<room name="Room #878" value="2"/>
		<room name="Room #879" value="2"/>
		<room name="Room #88" value="2"/>
		<room name="Room #880" value="2"/>
		<room name="Room #881" value="2"/>
		<room name="Room #882" value="2"/>
		<room name="Room #883" value="2"/>
		<room name="Room #884" value="2"/>
		<room name="Room #885" value="2"/>
		<room name="Room #886" value="2"/>
		<room name="Room #887" value="2"/>
		<room name="Room #888" value="2"/>
		<room name="Room #889" value="2"/>
		<room name="Room #89" value="2"/>
		<room name="Room #890" value="2"/>
		<room name="Room #891" value="2"/>
		<room name="Room #892" value="2"/>
		<room name="Room #893" value="2"/>
		<room name="Room #894" value="2"/>
		<room name="Room #895" value="2"/>
		<room name="Room #896" value="2"/>
		<room name="Room #897" value="2"/>
		<room name="Room #898" value="2"/>
		<room name="Room #899" value="2"/>
		<room name="Room #9" value="2"/>
		<room name="Room #90" value="2"/>
		<room name="Room #900" value="2"/>
		<room name="Room #901" value="2"/>
		<room name="Room #902" value="2"/>
		<room name="Room #903" value="2"/>
		<room name="Room #904" value="2"/>
		<room name="Room #905" value="2"/>
		<room name="Room #906" value="2"/>
		<room name="Room #907" value="2"/>
		<room name="Room #908" value="2"/>
		<room name="Room #909" value="2"/>
		<room name="Room #91" value="2"/>
		<room name="Room #910" value="2"/>
		<room name="Room #911" value="2"/>
		<room name="Room #912" value="2"/>
		<room name="Room #913" value="2"/>
		<room name="Room #914" value="2"/>
		<room name="Room #915" value="2"/>
		<room name="Room #916" value="2"/>
		<room name="Room #917" value="2"/>
		<room name="Room #918" value="2"/>
		<room name="Room #919" value="2"/>
		<room name="Room #92" value="2"/>
		<room name="Room #920" value="2"/>
		<room name="Room #921" value="2"/>
		<room name="Room #922" value="2"/>
		<room name="Room #923" value="2"/>
		<room name="Room #924" value="2"/>
		<room name="Room #925" value="2"/>
		<room name="Room #926" value="2"/>
		<room name="Room #927" value="2"/>
		<room name="Room #928" value="2"/>
		<room name="Room #929" value="2"/>
		<room name="Room #93" value="2"/>
		<room name="Room #930" value="2"/>
		<room name="Room #931" value="2"/>
		<room name="Room #932" value="2"/>
		<room name="Room #933" value="2"/>
		<room name="Room #934" value="2"/>
		<room name="Room #935" value="2"/>
		<room name="Room #936" value="2"/>
		<room name="Room #937" value="2"/>
		<room name="Room #938" value="2"/>
		<room name="Room #939" value="2"/>
		<room name="Room #94" value="2"/>
		<room name="Room #940" value="2"/>
		<room name="Room #941" value="2"/>
		<room name="Room #942" value="2"/>
		<room name="Room #943" value="2"/>
		<room name="Room #944" value="2"/>
		<room name="Room #945" value="2"/>
		<room name="Room #946" value="2"/>
		<room name="Room #947" value="2"/>
		<room name="Room #948" value="2"/>
		<room name="Room #949" value="2"/>
		<room name="Room #95" value="2"/>
		<room name="Room #950" value="2"/>
		<room name="Room #951" value="2"/>
		<room name="Room #952" value="2"/>
		<room name="Room #953" value="2"/>
		<room name="Room #954" value="2"/>
		<room name="Room #955" value="2"/>
		<room name="Room #956" value="2"/>
		<room name="Room #957" value="2"/>
		<room name="Room #958" value="2"/>
		<room name="Room #959" value="2"/>
		<room name="Room #96" value="2"/>
		<room name="Room #960" value="2"/>
		<room name="Room #961" value="2"/>
		<room name="Room #962" value="2"/>
		<room name="Room #963" value="2"/>
		<room name="Room #964" value="2"/>
		<room name="Room #965" value="2"/>
		<room name="Room #966" value="2"/>
		<room name="Room #967" value="2"/>
		<room name="Room #968" value="2"/>
		<room name="Room #969" value="2"/>
		<room name="Room #97" value="2"/>
		<room name="Room #970" value="2"/>
		<room name="Room #971" value="2"/>
		<room name="Room #972" value="2"/>
		<room name="Room #973" value="2"/>
		<room name="Room #974" value="2"/>
		<room name="Room #975" value="2"/>
		<room name="Room #976" value="2"/>
		<room name="Room #977" value="2"/>
		<room name="Room #978" value="2"/>
		<room name="Room #979" value="2"/>
		<room name="Room #98" value="2"/>
		<room name="Room #980" value="2"/>
		<room name="Room #981" value="2"/>
		<room name="Room #982" value="2"/>
		<room name="Room #983" value="2"/>
		<room name="Room #984" value="2"/>
		<room name="Room #985" value="2"/>
		<room name="Room #986" value="2"/>
		<room name="Room #987" value="2"/>
		<room name="Room #988" value="2"/>
		<room name="Room #989" value="2"/>
		<room name="Room #99" value="2"/>
		<room name="Room #990" value="2"/>
		<room name="Room #991" value="2"/>
		<room name="Room #992" value="2"/>
		<room name="Room #993" value="2"/>
		<room name="Room #994" value="2"/>
		<room name="Room #995" value="2"/>
		<room name="Room #996" value="2"/>
		<room name="Room #997" value="2"/>
		<room name="Room #998" value="2"/>
		<room name="Room #999" value="2"/>
	</rooms_with_different_sex_students>
	<working_time>
		<room name="show_rooms_with_different_sex_students" value="0.0651357"/>
		<room name="show_rooms_with_students_count" value="0.170886"/>
		<room name="show_top5_rooms_with_max_age_diff" value="0.027725"/>
		<room name="show_top5_rooms_with_min_average_age" value="0.0378687"/>
	</working_time>
</root>
